arrayfactor/__init__.py
arrayfactor/af.py
arrayfactor-1.0.3.dist-info/METADATA
arrayfactor-1.0.3.dist-info/WHEEL
arrayfactor-1.0.3.dist-info/top_level.txt
arrayfactor-1.0.3.dist-info/RECORD
